setup.py
AneMetroHexo.egg-info/PKG-INFO
AneMetroHexo.egg-info/SOURCES.txt
AneMetroHexo.egg-info/dependency_links.txt
AneMetroHexo.egg-info/top_level.txt
anemetrohexo/__init__.py
anemetrohexo/hexo.py