Metadata-Version: 1.1
Name: AneMetroHexo
Version: 0.0.1.dev4
Summary: Hexo site generator support for AneMetro
Home-page: https://github.com/pypa/sampleproject
Author: David Roberts
Author-email: pypi@teapotcoder.com
License: MIT
Keywords: anemetro hexo static
Platform: UNKNOWN
Classifier: Development Status :: 3 - Alpha
Classifier: Intended Audience :: Developers
Classifier: Topic :: Software Development :: Build Tools
Classifier: License :: OSI Approved :: MIT License
Classifier: Programming Language :: Python :: 2
Classifier: Programming Language :: Python :: 3
Classifier: Programming Language :: Python :: 3.3
Classifier: Programming Language :: Python :: 3.4
Classifier: Programming Language :: Python :: 3.5
